scimath/_version.py
scimath/__init__.py
scimath/physical_quantities/units.py
scimath/physical_quantities/dimensions.py
scimath/physical_quantities/util.py
scimath/physical_quantities/__init__.py
scimath/physical_quantities/tests/test_utils.py
scimath/physical_quantities/tests/test_units.py
scimath/physical_quantities/tests/test_dimensions.py
scimath/physical_quantities/tests/__init__.py
scimath/interpolate/api.py
scimath/interpolate/fitting.py
scimath/interpolate/_interpolate.cpython-38-aarch64-linux-gnu.so
scimath/interpolate/interpolate.py
scimath/interpolate/__init__.py
scimath/interpolate/tests/test_basic.py
scimath/interpolate/tests/__init__.py
scimath/mathematics/api.py
scimath/mathematics/quaternion.py
scimath/mathematics/__init__.py
scimath/units/api.py
scimath/units/has_units.py
scimath/units/geo_units.py
scimath/units/unit_converter.py
scimath/units/meta_quantity.py
scimath/units/unit_system.py
scimath/units/style_manager.py
scimath/units/electromagnetism.py
scimath/units/quantity_trait.py
scimath/units/temperature.py
scimath/units/family_name_trait.py
scimath/units/quantity_traits.py
scimath/units/acceleration.py
scimath/units/dimensionless.py
scimath/units/unit_db.py
scimath/units/density.py
scimath/units/frequency.py
scimath/units/angle.py
scimath/units/force.py
scimath/units/length.py
scimath/units/SI.py
scimath/units/scalar.py
scimath/units/variable.py
scimath/units/convert.py
scimath/units/volume.py
scimath/units/unit.py
scimath/units/function_signature.py
scimath/units/time.py
scimath/units/unit_parser.py
scimath/units/unit_traits.py
scimath/units/area.py
scimath/units/mass.py
scimath/units/unit_manager.py
scimath/units/unit_scalar.py
scimath/units/energy.py
scimath/units/power.py
scimath/units/unit_manipulation.py
scimath/units/quantity.py
scimath/units/smart_unit.py
scimath/units/speed.py
scimath/units/substance.py
scimath/units/__init__.py
scimath/units/pressure.py
scimath-5.0.0.dist-info/top_level.txt
scimath-5.0.0.dist-info/WHEEL
scimath-5.0.0.dist-info/METADATA
scimath-5.0.0.dist-info/RECORD
scimath-5.0.0.dist-info/LICENSE.txt
